kiwoomRest/__init__.py
kiwoomRest/rest_api.py
kiwoomRest/tr_code_to_path.py
kiwoomrest-0.0.1.dist-info/METADATA
kiwoomrest-0.0.1.dist-info/WHEEL
kiwoomrest-0.0.1.dist-info/licenses/LICENSE
kiwoomrest-0.0.1.dist-info/RECORD
