Metadata-Version: 2.3
Name: kiwoomRest
Version: 0.0.1
Summary: package for Kiwoom RestAPI
Project-URL: Homepage, https://github.com/teranum/python-packages/tree/master/kiwoomRest
Author-email: teranum <teranum@gmail.com>
Classifier: License :: OSI Approved :: MIT License
Classifier: Operating System :: OS Independent
Classifier: Programming Language :: Python :: 3
Requires-Python: >=3.8
Requires-Dist: aiohttp
